auxous/__init__.py
auxous-1.1.dist-info/LICENSE.txt
auxous-1.1.dist-info/METADATA
auxous-1.1.dist-info/WHEEL
auxous-1.1.dist-info/top_level.txt
auxous-1.1.dist-info/RECORD
