Metadata-Version: 2.1
Name: auxous
Version: 1.1
Summary: This is description part
Home-page: UNKNOWN
Author: UNKNOWN
Author-email: UNKNOWN
License: UNKNOWN
Platform: UNKNOWN
